{"frameRate":30,"isGlobal":0,"armature":[{"ik":[],"type":"Armature","bone":[{"name":"root","transform":{}},{"length":154,"transform":{"y":84.43,"skX":-88.14,"skY":-88.14,"x":-1.62},"parent":"root","name":"di_2"},{"length":154,"transform":{"y":84.43,"skX":-88.14,"skY":-88.14,"x":-1.62},"parent":"root","name":"di_3"},{"transform":{"scX":1.94,"y":-74.02,"scY":1.94,"skX":-135.15,"skY":-135.15,"x":88.93},"name":"dianguan6","parent":"root"},{"length":45,"transform":{"y":-52.21,"skX":138.01,"skY":138.01,"x":-31.64},"parent":"root","name":"ptex0102_01"},{"transform":{},"name":"shizi-di","parent":"root"},{"transform":{"scX":0.961,"y":42.1,"scY":0.961,"skX":-65.22,"skY":-65.22,"x":33.23},"name":"dianguan4","parent":"root"},{"transform":{"scX":1.365,"y":37.96,"scY":1.365,"skX":-65.22,"skY":-65.22,"x":-66.3},"name":"dianguan5","parent":"root"},{"length":125,"transform":{"y":61.17,"skX":-1.38,"skY":-1.38,"x":-142.45},"parent":"root","name":"shizi"},{"transform":{"scX":0.71,"y":-13.36,"scY":0.71,"skX":-26.76,"skY":-26.76,"x":-12.53},"name":"dianguan7","parent":"root"},{"transform":{"y":74.56,"x":-3.61},"name":"zi-di","parent":"root"},{"transform":{"scX":0.858,"y":-33.44,"scY":0.858,"skX":88.14,"skY":88.14,"x":110.71},"name":"dianguan","parent":"di_2"},{"transform":{"y":-81.42,"skX":88.14,"skY":88.14,"x":66.15},"name":"dianguan3","parent":"di_2"},{"transform":{"scX":0.914,"y":-65.05,"scY":0.914,"skX":88.14,"skY":88.14,"x":85.54},"name":"xingxing","parent":"di_2"},{"transform":{"scX":0.877,"y":-48.25,"scY":0.877,"skX":88.14,"skY":88.14,"x":100.91},"name":"xingxing2","parent":"di_2"},{"transform":{"y":-2.23,"skX":88.14,"skY":88.14,"x":138.9},"name":"dianguan2","parent":"di_2"}],"aabb":{"width":355,"y":-133.98049738978554,"height":250.68049738978553,"x":-211.07399155413765},"slot":[{"color":{},"name":"shizi-di","parent":"shizi-di"},{"z":1,"color":{},"name":"di_2","parent":"di_2"},{"blendMode":"add","z":2,"color":{},"name":"di_3","parent":"di_3"},{"blendMode":"add","z":3,"color":{},"name":"dianguan","parent":"dianguan"},{"blendMode":"add","z":4,"color":{},"name":"dianguan2","parent":"dianguan2"},{"blendMode":"add","z":5,"color":{},"name":"dianguan3","parent":"dianguan3"},{"blendMode":"add","z":6,"color":{},"name":"xingxing","parent":"xingxing"},{"blendMode":"add","z":7,"color":{},"name":"xingxing2","parent":"xingxing2"},{"z":8,"color":{},"name":"shizi","parent":"shizi"},{"blendMode":"add","z":9,"color":{},"name":"dianguan4","parent":"dianguan4"},{"blendMode":"add","z":10,"color":{},"name":"dianguan5","parent":"dianguan5"},{"blendMode":"add","z":11,"color":{},"name":"dianguan6","parent":"dianguan6"},{"blendMode":"add","z":12,"color":{},"name":"dianguan7","parent":"dianguan7"},{"z":13,"color":{},"name":"zi-di","parent":"zi-di"},{"z":14,"color":{},"name":"ziti","parent":"zi-di"},{"blendMode":"add","z":15,"color":{"gM":64,"bM":12},"name":"ptex0102_01","parent":"ptex0102_01"}],"defaultActions":[{"gotoAndPlay":"animation"}],"animation":[{"duration":75,"frame":[],"ik":[],"bone":[{"frame":[{"duration":75,"transform":{}},{"duration":0,"transform":{}}],"name":"root"},{"frame":[{"duration":75,"transform":{}},{"duration":0,"transform":{}}],"name":"shizi-di"},{"frame":[{"duration":20,"transform":{}},{"duration":5,"transform":{},"tweenEasing":0},{"duration":5,"transform":{"scX":0.954,"scY":1.045},"tweenEasing":0},{"duration":3,"transform":{"scX":1.066,"scY":0.955},"tweenEasing":0},{"duration":3,"transform":{"scX":0.992,"scY":1.023},"tweenEasing":0},{"duration":3,"transform":{"scX":1.022,"scY":0.969},"tweenEasing":0},{"duration":36,"transform":{}},{"duration":0,"transform":{}}],"name":"di_2"},{"frame":[{"duration":40,"transform":{},"tweenEasing":0},{"duration":10,"transform":{"scX":0.425,"scY":0.425},"tweenEasing":0},{"duration":5,"transform":{},"tweenEasing":0},{"duration":20,"transform":{"scX":0.805,"scY":0.805,"skX":79.16,"skY":79.16},"tweenEasing":0},{"duration":0,"transform":{}}],"name":"dianguan"},{"frame":[{"duration":35,"transform":{},"tweenEasing":0},{"duration":40,"transform":{"skX":49.32,"skY":49.32},"tweenEasing":0},{"duration":0,"transform":{}}],"name":"xingxing"},{"frame":[{"duration":75,"transform":{}},{"duration":0,"transform":{}}],"name":"zi-di"},{"frame":[{"duration":35,"transform":{},"tweenEasing":0},{"duration":40,"transform":{"scX":0.984,"y":0.32,"scY":0.965,"skX":-0.99,"skY":-0.99,"x":0.2},"tweenEasing":0},{"duration":0,"transform":{}}],"name":"shizi"},{"frame":[{"duration":35,"transform":{},"tweenEasing":0},{"duration":40,"transform":{"skX":-79.91,"skY":-79.91},"tweenEasing":0},{"duration":0,"transform":{}}],"name":"xingxing2"},{"frame":[{"duration":55,"transform":{},"tweenEasing":0},{"duration":10,"transform":{"scX":0.426,"scY":0.426},"tweenEasing":0},{"duration":5,"transform":{},"tweenEasing":0},{"duration":5,"transform":{"scX":0.794,"scY":0.794,"skX":78.11,"skY":78.11},"tweenEasing":0},{"duration":0,"transform":{}}],"name":"dianguan2"},{"frame":[{"duration":20,"transform":{},"tweenEasing":0},{"duration":10,"transform":{"scX":0.424,"scY":0.424},"tweenEasing":0},{"duration":5,"transform":{},"tweenEasing":0},{"duration":40,"transform":{"scX":0.754,"scY":0.754,"skX":63.44,"skY":63.44},"tweenEasing":0},{"duration":0,"transform":{}}],"name":"dianguan3"},{"frame":[{"duration":5,"transform":{},"tweenEasing":0},{"duration":10,"transform":{"scX":0.35,"scY":0.35},"tweenEasing":0},{"duration":5,"transform":{},"tweenEasing":0},{"duration":55,"transform":{"scX":0.61,"scY":0.61,"skX":213.9,"skY":213.9}}],"name":"dianguan4"},{"frame":[{"duration":25,"transform":{},"tweenEasing":0},{"duration":10,"transform":{"scX":0.453,"scY":0.453},"tweenEasing":0},{"duration":5,"transform":{},"tweenEasing":0},{"duration":35,"transform":{"scX":0.78,"scY":0.78,"skX":218.76,"skY":218.76}}],"name":"dianguan5"},{"frame":[{"duration":45,"transform":{},"tweenEasing":0},{"duration":10,"transform":{"scX":0.441,"scY":0.441},"tweenEasing":0},{"duration":5,"transform":{},"tweenEasing":0},{"duration":15,"transform":{"scX":0.722,"scY":0.722,"skX":90.73,"skY":90.73}}],"name":"dianguan7"},{"frame":[{"duration":60,"transform":{},"tweenEasing":0},{"duration":10,"transform":{"scX":0.594,"y":0.91,"scY":0.594},"tweenEasing":0},{"duration":5,"transform":{"y":-0.91,"x":1.37},"tweenEasing":0},{"duration":0,"transform":{"scX":0.785,"scY":0.785,"skX":249.04,"skY":249.04}}],"name":"dianguan6"},{"frame":[{"duration":20,"transform":{}},{"duration":5,"transform":{},"tweenEasing":0},{"duration":5,"transform":{"scX":0.954,"scY":1.045},"tweenEasing":0},{"duration":3,"transform":{"scX":1.066,"scY":0.955},"tweenEasing":0},{"duration":3,"transform":{"scX":0.992,"scY":1.023},"tweenEasing":0},{"duration":3,"transform":{"scX":1.022,"scY":0.969},"tweenEasing":0},{"duration":36,"transform":{}},{"duration":0,"transform":{}}],"name":"di_3"},{"frame":[{"duration":10,"transform":{"scX":0.453,"y":-31.57,"x":34.1},"tweenEasing":0},{"duration":10,"transform":{},"tweenEasing":0},{"duration":55,"transform":{"scX":0.543,"y":59.78,"x":-66.93}}],"name":"ptex0102_01"}],"slot":[{"frame":[{"tweenEasing":0,"duration":10,"color":{"aM":0}},{"tweenEasing":0,"duration":10,"color":{"aM":49}},{"tweenEasing":null,"duration":55,"color":{"aM":0}}],"name":"di_3"},{"frame":[{"tweenEasing":null,"duration":40,"color":{"aM":0}},{"tweenEasing":0,"duration":10,"color":{"aM":0}},{"tweenEasing":0,"duration":5},{"tweenEasing":null,"duration":20,"color":{"aM":0}}],"name":"dianguan"},{"frame":[{"tweenEasing":null,"duration":55,"color":{"aM":0}},{"tweenEasing":0,"duration":10,"color":{"aM":0}},{"tweenEasing":0,"duration":5},{"tweenEasing":null,"duration":5,"color":{"aM":0}}],"name":"dianguan2"},{"frame":[{"tweenEasing":null,"duration":20,"color":{"aM":0}},{"tweenEasing":0,"duration":10,"color":{"aM":0}},{"tweenEasing":0,"duration":5},{"tweenEasing":null,"duration":40,"color":{"aM":0}}],"name":"dianguan3"},{"frame":[{"tweenEasing":null,"duration":5,"color":{"aM":0}},{"tweenEasing":0,"duration":10,"color":{"aM":0}},{"tweenEasing":0,"duration":5},{"tweenEasing":null,"duration":55,"color":{"aM":0}}],"name":"dianguan4"},{"frame":[{"tweenEasing":null,"duration":25,"color":{"aM":0}},{"tweenEasing":0,"duration":10,"color":{"aM":0}},{"tweenEasing":0,"duration":5},{"tweenEasing":null,"duration":35,"color":{"aM":0}}],"name":"dianguan5"},{"frame":[{"tweenEasing":null,"duration":60,"color":{"aM":0}},{"tweenEasing":0,"duration":10,"color":{"aM":0}},{"tweenEasing":0,"duration":5},{"tweenEasing":null,"duration":0,"color":{"aM":0}}],"name":"dianguan6"},{"frame":[{"tweenEasing":null,"duration":45,"color":{"aM":0}},{"tweenEasing":0,"duration":10,"color":{"aM":0}},{"tweenEasing":0,"duration":5},{"tweenEasing":null,"duration":15,"color":{"aM":0}}],"name":"dianguan7"},{"frame":[{"tweenEasing":0,"duration":5,"color":{"gM":63,"bM":11,"aM":0}},{"tweenEasing":null,"duration":5,"color":{"gM":63,"bM":11}},{"tweenEasing":null,"duration":5,"color":{"gM":63,"bM":11}},{"tweenEasing":0,"duration":5,"color":{"gM":63,"bM":11}},{"tweenEasing":null,"duration":55,"color":{"gM":63,"bM":11,"aM":0}}],"name":"ptex0102_01"}],"ffd":[],"name":"animation"}],"frameRate":30,"name":"armatureName","skin":[{"name":"","slot":[{"display":[{"path":"dianguan","type":"image","name":"dianguan","transform":{"y":-1.12,"x":-0.09}}],"blendMode":"add","name":"dianguan6"},{"display":[{"path":"xingxing","type":"image","name":"xingxing","transform":{"y":-0.16,"x":0.86}}],"blendMode":"add","name":"xingxing"},{"display":[{"path":"dianguan","type":"image","name":"dianguan","transform":{"y":-1.12,"x":-0.09}}],"blendMode":"add","name":"dianguan4"},{"display":[{"path":"dianguan","type":"image","name":"dianguan","transform":{"y":-1.12,"x":-0.09}}],"blendMode":"add","name":"dianguan2"},{"display":[{"path":"dianguan","type":"image","name":"dianguan","transform":{"y":-1.12,"x":-0.09}}],"blendMode":"add","name":"dianguan"},{"display":[{"path":"di_2","type":"image","name":"di_2","transform":{"y":-1.21,"skX":88.14,"skY":88.14,"x":80.62}}],"blendMode":"add","name":"di_3"},{"display":[{"path":"di_2","type":"image","name":"di_2","transform":{"y":-1.21,"skX":88.14,"skY":88.14,"x":80.62}}],"name":"di_2"},{"display":[{"path":"dianguan","type":"image","name":"dianguan","transform":{"y":-1.12,"x":-0.09}}],"blendMode":"add","name":"dianguan7"},{"display":[{"path":"dianguan","type":"image","name":"dianguan","transform":{"y":-1.12,"x":-0.09}}],"blendMode":"add","name":"dianguan5"},{"display":[{"path":"zi-di","type":"image","name":"zi-di","transform":{"y":2.25,"x":8.16}}],"name":"zi-di"},{"display":[{"path":"shizi-di","type":"image","name":"shizi-di","transform":{}}],"name":"shizi-di"},{"display":[{"path":"ptex0102_01","type":"image","name":"ptex0102_01","transform":{"scX":0.442,"y":0.38,"scY":0.442,"skX":-167.89,"skY":-167.89,"x":2.26}}],"blendMode":"add","name":"ptex0102_01"},{"display":[{"path":"ziti","type":"image","name":"ziti","transform":{"y":2.64,"x":2.08}}],"name":"ziti"},{"display":[{"path":"xingxing","type":"image","name":"xingxing","transform":{"y":-0.16,"x":0.86}}],"blendMode":"add","name":"xingxing2"},{"display":[{"path":"dianguan","type":"image","name":"dianguan","transform":{"y":-1.12,"x":-0.09}}],"blendMode":"add","name":"dianguan3"},{"display":[{"path":"shizi","type":"image","name":"shizi","transform":{"y":-50.85,"skX":1.38,"skY":1.38,"x":135.07}}],"name":"shizi"}]}]}],"name":"szwg","version":"5.0"}