{"imagePath":"lyzz3d_tex.png","width":512,"SubTexture":[{"width":291,"y":1,"height":226,"name":"zzmj3d/bg","x":1},{"width":178,"y":1,"height":182,"name":"zzmj3d/main","x":294},{"width":78,"y":185,"height":62,"name":"zzmj3d/shaizi2_0","x":305},{"width":219,"y":426,"height":112,"name":"zzmj3d/muni","x":1},{"width":39,"y":240,"height":40,"name":"zzmj3d/shaizi2","x":452},{"width":28,"y":1,"height":28,"name":"zzmj3d/shaizi1","x":474},{"width":89,"y":185,"height":53,"name":"zzmj3d/coin2","x":385},{"width":65,"y":240,"height":38,"name":"zzmj3d/coin","x":385},{"width":227,"y":496,"height":63,"name":"zzmj3d/l2","x":222},{"width":302,"y":229,"height":195,"name":"zzmj3d/l1","x":1},{"width":269,"y":561,"height":50,"name":"zzmj3d/name_bg","x":1},{"width":252,"y":426,"height":68,"name":"zzmj3d/name","x":222}],"height":1024,"name":"lyzz3d"}